cs/hashutils.py
cs_hashutils-20250414.1.dist-info/WHEEL
cs_hashutils-20250414.1.dist-info/METADATA
cs_hashutils-20250414.1.dist-info/RECORD
